{
    "ID": 112,
    "BodRegion": "T",
    "BodRegionCislo": "0110",
    "IdFotografieZdroje": "0274",
    "CisloSANEPID": "",
    "CisloEGHeoM": "",
    "DokumetanceASM": "",
    "DBCisloWaterDataCentreMoldava": "",
    "Obec": "Aluatu",
    "ZastupceSamospravy": "Doncev Dumitru,078324684",
    "BlizsiLokalizace": "str.31 august 19",
    "KatastralniCislo": "",
    "CharekterPozemku": "",
    "SouradniceBobuXstupne": "28,00",
    "SouradniceBobuXminuty": 35,
    "SouradniceBobuXvteriny": "1,00",
    "SouradniceBoduYstupne": "45,00",
    "SouradniceBoduYminuty": 51,
    "SouradniceBoduYvteriny": "53,00",
    "NadmorskaVyskaBodu": -2,
    "DodatkovaInformace": "",
    "CharakterZdrojeVody": "Fântâna săpată",
    "HloubkaStudnyMerena": "6,00",
    "HloubkaStudnyLocalInfo": "7,50",
    "HloubkaHladinyMerena": "7,50",
    "HloubkaHladinyLocalInfo": "6,00",
    "PrumerStudny": "1000,00",
    "VydatnosZdroje": "",
    "VydatnostPokles": 0,
    "HladinaPodzemVody": 0,
    "ZrizovatlZdroje": "Tocarciuc Anatol",
    "ZrizeniDatum": 1990,
    "ObsluhaObyvatel": 12,
    "DulezitostProObec": "Imporanţă mică – faţă de sursele celelalte",
    "Morfologie": "Suprafaţă plană – câmpie",
    "Pokryv": "Suprafaţa construită urbană/rurală",
    "GeologiePovrch": "Sol",
    "GeologiePodlozi": "",
    "GeologieLitologie": "",
    "GeologieOblast": "",
    "GeologieHydrogeologie": "",
    "HydrogeologieKolektor": "",
    "DokumentaceZdroje": 0,
    "PovrchoveTesneni": "Coroana fântânii cimentată",
    "Plot": "",
    "OchrannePasmo": "",
    "ObecnaOchrana": "",
    "PovrchovaVodaVztah": "Apă de suprafaţă nu se acumulează în împrejurime niciodată",
    "TokVztah": "Nu e inundat niciodata",
    "SilniceVzdalenost": "15,00",
    "ZdrojZnecisteni": "Băligar (îngrăşământ) uzual",
    "ZdrojZnecisteniPopis": "",
    "SouradniceZnecisteniXstupne": "28,00",
    "SouradniceZnecisteniXminuty": 35,
    "SouradniceZnecisteniXvteriny": "1,00",
    "SouradniceZnecisteniYstupne": "45,00",
    "SouradniceZnecisteniYminuty": 51,
    "SouradniceZnecisteniYvteriny": "53,00",
    "NamorskaVyskaZnecisteniX": -2,
    "ZnecisteniFoto": "0275",
    "OrganleptickeZnecisteni": "nimic",
    "Zakal": "Nimic",
    "ZavadnostMistniInformace": 0,
    "DobraVodaMistniInformace": 1,
    "Teplota": "16,10",
    "EC": "4,01",
    "O2MgL": "9,55",
    "O2procenta": "96,60",
    "pH": "7,78",
    "EH": "349,00",
    "OdberVzorku": "",
    "DatumVznikuZaznmu": "7.5.2014 0:00:00",
    "DatumPosledniUpravy": "7.5.2014 17:34:13",
    "OdberovaSkupina": "U001"
}