{
    "ID": 193,
    "BodRegion": "T",
    "BodRegionCislo": "0191",
    "IdFotografieZdroje": "0457",
    "CisloSANEPID": "",
    "CisloEGHeoM": "",
    "DokumetanceASM": "",
    "DBCisloWaterDataCentreMoldava": "",
    "Obec": "Ciumai",
    "ZastupceSamospravy": "Turcan Tatiana,078800288",
    "BlizsiLokalizace": "str.Gagarina 46",
    "KatastralniCislo": "",
    "CharekterPozemku": "",
    "SouradniceBobuXstupne": "28,00",
    "SouradniceBobuXminuty": 34,
    "SouradniceBobuXvteriny": "1,00",
    "SouradniceBoduYstupne": "45,00",
    "SouradniceBoduYminuty": 46,
    "SouradniceBoduYvteriny": "55,00",
    "NadmorskaVyskaBodu": 21,
    "DodatkovaInformace": "",
    "CharakterZdrojeVody": "Fântâna săpată",
    "HloubkaStudnyMerena": "10,10",
    "HloubkaStudnyLocalInfo": "12,00",
    "HloubkaHladinyMerena": "12,00",
    "HloubkaHladinyLocalInfo": "10,10",
    "PrumerStudny": "100,00",
    "VydatnosZdroje": "",
    "VydatnostPokles": 0,
    "HladinaPodzemVody": 0,
    "ZrizovatlZdroje": "Vihadet Anatolii",
    "ZrizeniDatum": 2000,
    "ObsluhaObyvatel": 10,
    "DulezitostProObec": "Imporanţă mică – faţă de sursele celelalte",
    "Morfologie": "Suprafaţă plană – câmpie",
    "Pokryv": "Suprafaţa construită urbană/rurală",
    "GeologiePovrch": "Sol",
    "GeologiePodlozi": "",
    "GeologieLitologie": "",
    "GeologieOblast": "",
    "GeologieHydrogeologie": "",
    "HydrogeologieKolektor": "",
    "DokumentaceZdroje": 0,
    "PovrchoveTesneni": "Coroana fântânii cimentată",
    "Plot": "",
    "OchrannePasmo": "",
    "ObecnaOchrana": "",
    "PovrchovaVodaVztah": "Apă de suprafaţă nu se acumulează în împrejurime niciodată",
    "TokVztah": "Nu e inundat niciodata",
    "SilniceVzdalenost": "6,00",
    "ZdrojZnecisteni": "Un alt mod de contaminare – descriere",
    "ZdrojZnecisteniPopis": "gradina particulara",
    "SouradniceZnecisteniXstupne": "28,00",
    "SouradniceZnecisteniXminuty": 34,
    "SouradniceZnecisteniXvteriny": "1,00",
    "SouradniceZnecisteniYstupne": "45,00",
    "SouradniceZnecisteniYminuty": 46,
    "SouradniceZnecisteniYvteriny": "55,00",
    "NamorskaVyskaZnecisteniX": 21,
    "ZnecisteniFoto": "0458",
    "OrganleptickeZnecisteni": "nimic",
    "Zakal": "Nimic",
    "ZavadnostMistniInformace": 0,
    "DobraVodaMistniInformace": 1,
    "Teplota": "13,70",
    "EC": "2,80",
    "O2MgL": "7,49",
    "O2procenta": "81,50",
    "pH": "7,89",
    "EH": "213,00",
    "OdberVzorku": "",
    "DatumVznikuZaznmu": "13.5.2014 0:00:00",
    "DatumPosledniUpravy": "13.5.2014 12:31:38",
    "OdberovaSkupina": "U001"
}