{
    "ID": 959,
    "BodRegion": "Ch",
    "BodRegionCislo": "0402",
    "IdFotografieZdroje": 2715,
    "CisloSANEPID": "",
    "CisloEGHeoM": "",
    "DokumetanceASM": "",
    "DBCisloWaterDataCentreMoldava": "",
    "Obec": "Badicul Moldovenesc",
    "ZastupceSamospravy": "Lucian Taban",
    "BlizsiLokalizace": "raspunzator Primaria",
    "KatastralniCislo": "",
    "CharekterPozemku": "",
    "SouradniceBobuXstupne": "28,00",
    "SouradniceBobuXminuty": 15,
    "SouradniceBobuXvteriny": "48,00",
    "SouradniceBoduYstupne": "46,00",
    "SouradniceBoduYminuty": 5,
    "SouradniceBoduYvteriny": "48,00",
    "NadmorskaVyskaBodu": 94,
    "DodatkovaInformace": "se afla in curte particulara\r\nse alimenteaza prin pompa 3 familii,circa 14 persoane",
    "CharakterZdrojeVody": "Fântâna săpată",
    "HloubkaStudnyMerena": "7,50",
    "HloubkaStudnyLocalInfo": "9,40",
    "HloubkaHladinyMerena": "9,40",
    "HloubkaHladinyLocalInfo": "7,50",
    "PrumerStudny": "1000,00",
    "VydatnosZdroje": "",
    "VydatnostPokles": 0,
    "HladinaPodzemVody": 0,
    "ZrizovatlZdroje": "localnici",
    "ZrizeniDatum": 1970,
    "ObsluhaObyvatel": 10,
    "DulezitostProObec": "Imporanţă mică – faţă de sursele celelalte",
    "Morfologie": "Suprafaţă plană – câmpie",
    "Pokryv": "Suprafaţa construită urbană/rurală",
    "GeologiePovrch": "Sol",
    "GeologiePodlozi": "",
    "GeologieLitologie": "",
    "GeologieOblast": "",
    "GeologieHydrogeologie": "",
    "HydrogeologieKolektor": "",
    "DokumentaceZdroje": 0,
    "PovrchoveTesneni": "Coroana fântânii cimentată",
    "Plot": "",
    "OchrannePasmo": "",
    "ObecnaOchrana": "",
    "PovrchovaVodaVztah": "Apă de suprafaţă nu se acumulează în împrejurime niciodată",
    "TokVztah": "Nu e inundat niciodata",
    "SilniceVzdalenost": "20,00",
    "ZdrojZnecisteni": "Un alt mod de contaminare – descriere",
    "ZdrojZnecisteniPopis": "gradina particulara",
    "SouradniceZnecisteniXstupne": "28,00",
    "SouradniceZnecisteniXminuty": 15,
    "SouradniceZnecisteniXvteriny": "48,00",
    "SouradniceZnecisteniYstupne": "46,00",
    "SouradniceZnecisteniYminuty": 5,
    "SouradniceZnecisteniYvteriny": "48,00",
    "NamorskaVyskaZnecisteniX": 94,
    "ZnecisteniFoto": 2716,
    "OrganleptickeZnecisteni": "",
    "Zakal": "Nimic",
    "ZavadnostMistniInformace": 0,
    "DobraVodaMistniInformace": 1,
    "Teplota": "14,10",
    "EC": "0,89",
    "O2MgL": "3,89",
    "O2procenta": "38,00",
    "pH": "7,56",
    "EH": "51,00",
    "OdberVzorku": "Proba de apă de suprafaţă (luată)",
    "DatumVznikuZaznmu": "18.9.2014 0:00:00",
    "DatumPosledniUpravy": "18.9.2014 11:42:07",
    "OdberovaSkupina": "U001"
}