{
    "ID": 137,
    "BodRegion": "T",
    "BodRegionCislo": "0135",
    "IdFotografieZdroje": "0324",
    "CisloSANEPID": "",
    "CisloEGHeoM": "",
    "DokumetanceASM": "",
    "DBCisloWaterDataCentreMoldava": "",
    "Obec": "Aluatu",
    "ZastupceSamospravy": "Doncev Dumitru,078324684",
    "BlizsiLokalizace": "str.Frunza 123",
    "KatastralniCislo": "",
    "CharekterPozemku": "",
    "SouradniceBobuXstupne": "28,00",
    "SouradniceBobuXminuty": 35,
    "SouradniceBobuXvteriny": "12,00",
    "SouradniceBoduYstupne": "45,00",
    "SouradniceBoduYminuty": 52,
    "SouradniceBoduYvteriny": "23,00",
    "NadmorskaVyskaBodu": 8,
    "DodatkovaInformace": "",
    "CharakterZdrojeVody": "Fântâna săpată",
    "HloubkaStudnyMerena": "9,00",
    "HloubkaStudnyLocalInfo": "10,80",
    "HloubkaHladinyMerena": "10,80",
    "HloubkaHladinyLocalInfo": "9,00",
    "PrumerStudny": "1000,00",
    "VydatnosZdroje": "",
    "VydatnostPokles": 0,
    "HladinaPodzemVody": 0,
    "ZrizovatlZdroje": "Tanoc Pavel",
    "ZrizeniDatum": 1940,
    "ObsluhaObyvatel": 10,
    "DulezitostProObec": "Imporanţă mică – faţă de sursele celelalte",
    "Morfologie": "Suprafaţă plană – câmpie",
    "Pokryv": "Suprafaţa construită urbană/rurală",
    "GeologiePovrch": "Sol",
    "GeologiePodlozi": "",
    "GeologieLitologie": "",
    "GeologieOblast": "",
    "GeologieHydrogeologie": "",
    "HydrogeologieKolektor": "",
    "DokumentaceZdroje": 0,
    "PovrchoveTesneni": "Coroana fântânii cimentată",
    "Plot": "",
    "OchrannePasmo": "",
    "ObecnaOchrana": "",
    "PovrchovaVodaVztah": "Apă de suprafaţă nu se acumulează în împrejurime niciodată",
    "TokVztah": "Nu e inundat niciodata",
    "SilniceVzdalenost": "17,00",
    "ZdrojZnecisteni": "Un alt mod de contaminare – descriere",
    "ZdrojZnecisteniPopis": "gradina particulara",
    "SouradniceZnecisteniXstupne": "28,00",
    "SouradniceZnecisteniXminuty": 35,
    "SouradniceZnecisteniXvteriny": "12,00",
    "SouradniceZnecisteniYstupne": "45,00",
    "SouradniceZnecisteniYminuty": 52,
    "SouradniceZnecisteniYvteriny": "23,00",
    "NamorskaVyskaZnecisteniX": 8,
    "ZnecisteniFoto": "0325",
    "OrganleptickeZnecisteni": "nimic",
    "Zakal": "Nimic",
    "ZavadnostMistniInformace": 0,
    "DobraVodaMistniInformace": 1,
    "Teplota": "12,50",
    "EC": "3,80",
    "O2MgL": "8,55",
    "O2procenta": "81,50",
    "pH": "7,87",
    "EH": "243,00",
    "OdberVzorku": "",
    "DatumVznikuZaznmu": "8.5.2014 0:00:00",
    "DatumPosledniUpravy": "8.5.2014 10:20:40",
    "OdberovaSkupina": "U001"
}