{
    "ID": 1412,
    "BodRegion": "Ch",
    "BodRegionCislo": "0855",
    "SampleId": "Ch0855",
    "NazevRegion": "Cahul",
    "Obec": "Cahul",
    "KatastralniCislo": "",
    "ZastupceSamospravy": "Chitaniuc Gavril",
    "CisloSANEPID": "",
    "CisloEGHeoM": "",
    "DokumetanceASM": "",
    "DBCisloWaterDataCentreMoldava": "",
    "SouradniceBobuXstupne": 28,
    "SouradniceBobuXminuty": 10,
    "SouradniceBobuXvteriny": 42,
    "SouradniceBoduYstupne": 45,
    "SouradniceBoduYminuty": 53,
    "SouradniceBoduYvteriny": 46,
    "NadmorskaVyskaBodu": 43,
    "IdFotografieZdroje": 3884,
    "BlizsiLokalizace": "raspunzator salubritatea",
    "BlizsiLokalizaceCZ": "odpovídá komunální hygiena",
    "DodatkovaInformace": "se afla la drum",
    "DodatkovaInformaceCZ": "nachází se u cesty",
    "CharakterZdrojeVody": "Izvor",
    "CharakterZdrojeVodyCz": "Pramen",
    "HloubkaHladinyLocalInfo": "",
    "HloubkaHladinyMerena": "",
    "HloubkaStudnyLocalInfo": "",
    "HloubkaStudnyMerena": "",
    "PrumerStudny": "",
    "VydatnosZdroje": 0,
    "VydatnostPokles": "FALSE",
    "HladinaPodzemVody": "FALSE",
    "ZrizovatlZdroje": "localnici",
    "ZrizovatlZdrojeCz": "místní obyvatelé",
    "ZrizeniDatum": 1970,
    "ObsluhaObyvatel": 50,
    "DulezitostProObec": "Importanță mică – faţă de sursele celelalte",
    "DůlezitostProObecCz": "Malý význam - vzhledem k ostatním zdrojům",
    "Morfologie": "Suprafaţă plană – câmpie",
    "Morfologiecz": "Ploché území - rovina",
    "Pokryv": "Suprafaţa construită urbană/rurală",
    "Pokryvcz": "Městská /vesnická zástavba",
    "GeologiePovrch": "Sol",
    "GeologiePovrchCz": "Zemina",
    "Pedologie": "Aluvional",
    "PedologieCz": "Aluviální (fluvizem)",
    "GeologiePodloziSymbol": "N2pn",
    "GeologiePodloziPopis": "Formatiuni pontice Calcare, Calcare cu insetii de cochilii, nisipuri, nisip Argilos",
    "GeologiePodloziPopisCz": "Pontské souvrství. Vápence, lasturnaté vápence, písky, hlíny, pískovce.",
    "GeologieLitologieCz": "Jíly s vložkami písků a pískovců",
    "GeologieLitologie": "Argile cu adaos de nisipuri şi gresii",
    "GeologieOblastSymbol": "Zona 3",
    "GeologieOblast": "Răspândirea calcarelor sarmaţiene.",
    "GeologieOblastCz": "Hranice rozšíření sarmatských vápenců.",
    "HydrogeologieSymbol": "N2pn",
    "HydrogeologieKolektor": "Strat acvifer în depozitele pontice. Calcare, nisipuri aleurite.",
    "HydrogeologieKolektorCz": "Zvodněný horizont v uloženinách pontského stupně. Vápence, písky, aleurity.",
    "DokumentaceZdroje": "FALSE",
    "PovrchoveTesneni": "Coroana fântânii cimentată",
    "PovrchoveTesneniCz": "Cementované mezikruží studny",
    "Plot": "",
    "OchrannePasmo": "",
    "ObecnaOchrana": "",
    "PovrchovaVodaVztah": "Apă de suprafaţă nu se acumulează în împrejurime niciodată",
    "PovrchovaVodaVztahCz": "Povrchová voda se v okolí nikdy nehromadí",
    "TokVztah": "Nu e inundat niciodata",
    "TokVztahCz": "Povodeň nikdy nezaplavuje",
    "SilniceVzdalenost": 20,
    "ZdrojZnecisteni": "Un alt mod de contaminare – descriere",
    "ZdrojZnecistenicz": "Jinak znečištěné místo - popsat",
    "ZdrojZnecisteniPopis": "traseul Cahul-Giurgiulesti",
    "ZdrojZnecisteniPopisCz": "trasa Cahul-Giurgiulesti",
    "SouradniceZnecisteniXstupne": 28,
    "SouradniceZnecisteniXminuty": 10,
    "SouradniceZnecisteniXvteriny": 43,
    "SouradniceZnecisteniYstupne": 45,
    "SouradniceZnecisteniYminuty": 53,
    "SouradniceZnecisteniYvteriny": 45,
    "NamorskaVyskaZnecisteniX": 43,
    "ZnecisteniFoto": 3885,
    "OrganleptickeZnecisteni": "",
    "OrganoleptickeZnecistenicz": "",
    "Zakal": "Nimic",
    "ZakalCZ": "Žádný",
    "ZavadnostMistniInformace": "FALSE",
    "DobraVodaMistniInformace": "TRUE",
    "Teplota": 11,
    "EC": 1,
    "O2MgL": 1,
    "O2procenta": 10,
    "pH": 8,
    "EH": -104,
    "cOdberVzorku": "Din apă curgătoare – robinet, apa adusă prin conducta izvorului",
    "cOdberVzorkuCz": "Z tekoucí vody – kohoutek vodovodu, výtok potrubím ze zachyceného pramene",
    "DatumVznikuZaznmu": "11/25/14",
    "DatumPosledniUpravy": "11/25/14",
    "OdberovaSkupina": "U001",
    "Tisk": "",
    "SouradniceBoduX": 28,
    "SouradniceBoduY": 45,
    "SouradniceZnecisteniX": 28,
    "SouradniceZnecisteniY": 45,
    "rozbory": 1,
    "rozbory2": "z",
    "zkontrolováno": 9,
    "uuid": "Ch0855"
}