{
    "ID": 1844,
    "BodRegion": "Lv",
    "BodRegionCislo": "0420",
    "IdFotografieZdroje": 4877,
    "CisloSANEPID": "",
    "CisloEGHeoM": "",
    "DokumetanceASM": "",
    "DBCisloWaterDataCentreMoldava": "",
    "Obec": "Beştemac",
    "ZastupceSamospravy": "Racila Ioana,primar",
    "BlizsiLokalizace": "pe teritoriul satului",
    "KatastralniCislo": "",
    "CharekterPozemku": "",
    "SouradniceBobuXstupne": "28,00",
    "SouradniceBobuXminuty": 31,
    "SouradniceBobuXvteriny": "47,00",
    "SouradniceBoduYstupne": "46,00",
    "SouradniceBoduYminuty": 31,
    "SouradniceBoduYvteriny": "47,00",
    "NadmorskaVyskaBodu": 73,
    "DodatkovaInformace": "raspunzator primaria",
    "CharakterZdrojeVody": "Fântâna săpată",
    "HloubkaStudnyMerena": "6,80",
    "HloubkaStudnyLocalInfo": "9,40",
    "HloubkaHladinyMerena": "9,40",
    "HloubkaHladinyLocalInfo": "6,80",
    "PrumerStudny": "1000,00",
    "VydatnosZdroje": "",
    "VydatnostPokles": 0,
    "HladinaPodzemVody": 0,
    "ZrizovatlZdroje": "localnici",
    "ZrizeniDatum": 1962,
    "ObsluhaObyvatel": 10,
    "DulezitostProObec": "Imporanţă mică – faţă de sursele celelalte",
    "Morfologie": "Suprafaţă plană – câmpie",
    "Pokryv": "Suprafaţa construită urbană/rurală",
    "GeologiePovrch": "Sol",
    "GeologiePodlozi": "",
    "GeologieLitologie": "",
    "GeologieOblast": "",
    "GeologieHydrogeologie": "",
    "HydrogeologieKolektor": "",
    "DokumentaceZdroje": 0,
    "PovrchoveTesneni": "Coroana fântânii cimentată",
    "Plot": "",
    "OchrannePasmo": "",
    "ObecnaOchrana": "",
    "PovrchovaVodaVztah": "Apă de suprafaţă nu se acumulează în împrejurime niciodată",
    "TokVztah": "Nu e inundat niciodata",
    "SilniceVzdalenost": "10,00",
    "ZdrojZnecisteni": "Un alt mod de contaminare – descriere",
    "ZdrojZnecisteniPopis": "drum de tara",
    "SouradniceZnecisteniXstupne": "28,00",
    "SouradniceZnecisteniXminuty": 31,
    "SouradniceZnecisteniXvteriny": "47,00",
    "SouradniceZnecisteniYstupne": "46,00",
    "SouradniceZnecisteniYminuty": 31,
    "SouradniceZnecisteniYvteriny": "47,00",
    "NamorskaVyskaZnecisteniX": 73,
    "ZnecisteniFoto": 4878,
    "OrganleptickeZnecisteni": "",
    "Zakal": "Nimic",
    "ZavadnostMistniInformace": 0,
    "DobraVodaMistniInformace": 1,
    "Teplota": "10,90",
    "EC": "6,11",
    "O2MgL": "8,09",
    "O2procenta": "74,50",
    "pH": "7,47",
    "EH": "60,00",
    "OdberVzorku": "",
    "DatumVznikuZaznmu": "1.4.2015 0:00:00",
    "DatumPosledniUpravy": "1.4.2015 11:24:36",
    "OdberovaSkupina": "U001"
}