{
    "ID": 1412,
    "BodRegion": "Ch",
    "BodRegionCislo": "0855",
    "IdFotografieZdroje": 3884,
    "CisloSANEPID": "",
    "CisloEGHeoM": "",
    "DokumetanceASM": "",
    "DBCisloWaterDataCentreMoldava": "",
    "Obec": "Cahul",
    "ZastupceSamospravy": "Chitaniuc Gavril",
    "BlizsiLokalizace": "raspunzator salubritatea",
    "KatastralniCislo": "",
    "CharekterPozemku": "",
    "SouradniceBobuXstupne": "28,00",
    "SouradniceBobuXminuty": 10,
    "SouradniceBobuXvteriny": "42,00",
    "SouradniceBoduYstupne": "45,00",
    "SouradniceBoduYminuty": 53,
    "SouradniceBoduYvteriny": "46,00",
    "NadmorskaVyskaBodu": 43,
    "DodatkovaInformace": "se afla la drum",
    "CharakterZdrojeVody": "Izvor",
    "HloubkaStudnyMerena": "",
    "HloubkaStudnyLocalInfo": "",
    "HloubkaHladinyMerena": "",
    "HloubkaHladinyLocalInfo": "",
    "PrumerStudny": "",
    "VydatnosZdroje": "0,20",
    "VydatnostPokles": 0,
    "HladinaPodzemVody": 0,
    "ZrizovatlZdroje": "localnici",
    "ZrizeniDatum": 1970,
    "ObsluhaObyvatel": 50,
    "DulezitostProObec": "Imporanţă mică – faţă de sursele celelalte",
    "Morfologie": "Suprafaţă plană – câmpie",
    "Pokryv": "Suprafaţa construită urbană/rurală",
    "GeologiePovrch": "Sol",
    "GeologiePodlozi": "",
    "GeologieLitologie": "",
    "GeologieOblast": "",
    "GeologieHydrogeologie": "",
    "HydrogeologieKolektor": "",
    "DokumentaceZdroje": 0,
    "PovrchoveTesneni": "Coroana fântânii cimentată",
    "Plot": "",
    "OchrannePasmo": "",
    "ObecnaOchrana": "",
    "PovrchovaVodaVztah": "Apă de suprafaţă nu se acumulează în împrejurime niciodată",
    "TokVztah": "Nu e inundat niciodata",
    "SilniceVzdalenost": "20,00",
    "ZdrojZnecisteni": "Un alt mod de contaminare – descriere",
    "ZdrojZnecisteniPopis": "traseul Cahul-Giurgiulesti",
    "SouradniceZnecisteniXstupne": "28,00",
    "SouradniceZnecisteniXminuty": 10,
    "SouradniceZnecisteniXvteriny": "43,00",
    "SouradniceZnecisteniYstupne": "45,00",
    "SouradniceZnecisteniYminuty": 53,
    "SouradniceZnecisteniYvteriny": "45,00",
    "NamorskaVyskaZnecisteniX": 43,
    "ZnecisteniFoto": 3885,
    "OrganleptickeZnecisteni": "",
    "Zakal": "Nimic",
    "ZavadnostMistniInformace": 0,
    "DobraVodaMistniInformace": 1,
    "Teplota": "11,10",
    "EC": "1,00",
    "O2MgL": "1,23",
    "O2procenta": "10,90",
    "pH": "8,19",
    "EH": "-104,00",
    "OdberVzorku": "Din apă curgătoare – robinet, apa adusă prin conducta izvorului",
    "DatumVznikuZaznmu": "25.11.2014 0:00:00",
    "DatumPosledniUpravy": "25.11.2014 11:21:03",
    "OdberovaSkupina": "U001"
}