{
    "ID": 1180,
    "BodRegion": "Ch",
    "BodRegionCislo": "0623",
    "IdFotografieZdroje": 3367,
    "CisloSANEPID": "",
    "CisloEGHeoM": "",
    "DokumetanceASM": "",
    "DBCisloWaterDataCentreMoldava": "",
    "Obec": "Moscovei",
    "ZastupceSamospravy": "Bucicovar Nicolai",
    "BlizsiLokalizace": "raspunzator Primaria",
    "KatastralniCislo": "",
    "CharekterPozemku": "",
    "SouradniceBobuXstupne": "28,00",
    "SouradniceBobuXminuty": 21,
    "SouradniceBobuXvteriny": "21,00",
    "SouradniceBoduYstupne": "45,00",
    "SouradniceBoduYminuty": 55,
    "SouradniceBoduYvteriny": "51,00",
    "NadmorskaVyskaBodu": 63,
    "DodatkovaInformace": "se afla la drum",
    "CharakterZdrojeVody": "Fântâna săpată",
    "HloubkaStudnyMerena": "3,80",
    "HloubkaStudnyLocalInfo": "5,00",
    "HloubkaHladinyMerena": "5,00",
    "HloubkaHladinyLocalInfo": "3,80",
    "PrumerStudny": "1000,00",
    "VydatnosZdroje": "",
    "VydatnostPokles": 0,
    "HladinaPodzemVody": 0,
    "ZrizovatlZdroje": "localnici",
    "ZrizeniDatum": 1963,
    "ObsluhaObyvatel": 10,
    "DulezitostProObec": "Imporanţă mică – faţă de sursele celelalte",
    "Morfologie": "Suprafaţă plană – câmpie",
    "Pokryv": "Suprafaţa construită urbană/rurală",
    "GeologiePovrch": "Sol",
    "GeologiePodlozi": "",
    "GeologieLitologie": "",
    "GeologieOblast": "",
    "GeologieHydrogeologie": "",
    "HydrogeologieKolektor": "",
    "DokumentaceZdroje": 0,
    "PovrchoveTesneni": "Coroana fântânii cimentată",
    "Plot": "",
    "OchrannePasmo": "",
    "ObecnaOchrana": "",
    "PovrchovaVodaVztah": "Apă de suprafaţă nu se acumulează în împrejurime niciodată",
    "TokVztah": "Nu e inundat niciodata",
    "SilniceVzdalenost": "4,00",
    "ZdrojZnecisteni": "Un alt mod de contaminare – descriere",
    "ZdrojZnecisteniPopis": "drum de tara",
    "SouradniceZnecisteniXstupne": "28,00",
    "SouradniceZnecisteniXminuty": 21,
    "SouradniceZnecisteniXvteriny": "21,00",
    "SouradniceZnecisteniYstupne": "45,00",
    "SouradniceZnecisteniYminuty": 55,
    "SouradniceZnecisteniYvteriny": "51,00",
    "NamorskaVyskaZnecisteniX": 63,
    "ZnecisteniFoto": 3368,
    "OrganleptickeZnecisteni": "",
    "Zakal": "Nimic",
    "ZavadnostMistniInformace": 0,
    "DobraVodaMistniInformace": 1,
    "Teplota": "15,10",
    "EC": "3,67",
    "O2MgL": "2,46",
    "O2procenta": "24,60",
    "pH": "7,55",
    "EH": "69,00",
    "OdberVzorku": "Proba de apă de suprafaţă (luată)",
    "DatumVznikuZaznmu": "14.10.2014 0:00:00",
    "DatumPosledniUpravy": "14.10.2014 11:33:35",
    "OdberovaSkupina": "U001"
}