{
    "ID": 1593,
    "BodRegion": "Lv",
    "BodRegionCislo": "0170",
    "IdFotografieZdroje": 4357,
    "CisloSANEPID": "",
    "CisloEGHeoM": "",
    "DokumetanceASM": "",
    "DBCisloWaterDataCentreMoldava": "",
    "Obec": "Cneazevca",
    "ZastupceSamospravy": "Tomsa Larisa,primar",
    "BlizsiLokalizace": "pe teritoriul satului",
    "KatastralniCislo": "",
    "CharekterPozemku": "",
    "SouradniceBobuXstupne": "28,00",
    "SouradniceBobuXminuty": 30,
    "SouradniceBobuXvteriny": "7,00",
    "SouradniceBoduYstupne": "46,00",
    "SouradniceBoduYminuty": 38,
    "SouradniceBoduYvteriny": "3,00",
    "NadmorskaVyskaBodu": 100,
    "DodatkovaInformace": "raspunzator primaria",
    "CharakterZdrojeVody": "Fântâna săpată",
    "HloubkaStudnyMerena": "7,10",
    "HloubkaStudnyLocalInfo": "9,00",
    "HloubkaHladinyMerena": "9,00",
    "HloubkaHladinyLocalInfo": "7,10",
    "PrumerStudny": "1000,00",
    "VydatnosZdroje": "",
    "VydatnostPokles": 0,
    "HladinaPodzemVody": 0,
    "ZrizovatlZdroje": "localnici",
    "ZrizeniDatum": 1980,
    "ObsluhaObyvatel": 10,
    "DulezitostProObec": "Imporanţă mică – faţă de sursele celelalte",
    "Morfologie": "Suprafaţă plană – câmpie",
    "Pokryv": "Suprafaţa construită urbană/rurală",
    "GeologiePovrch": "Sol",
    "GeologiePodlozi": "",
    "GeologieLitologie": "",
    "GeologieOblast": "",
    "GeologieHydrogeologie": "",
    "HydrogeologieKolektor": "",
    "DokumentaceZdroje": 0,
    "PovrchoveTesneni": "Coroana fântânii cimentată",
    "Plot": "",
    "OchrannePasmo": "",
    "ObecnaOchrana": "",
    "PovrchovaVodaVztah": "Apă de suprafaţă nu se acumulează în împrejurime niciodată",
    "TokVztah": "Nu e inundat niciodata",
    "SilniceVzdalenost": "8,00",
    "ZdrojZnecisteni": "Un alt mod de contaminare – descriere",
    "ZdrojZnecisteniPopis": "drum de tara",
    "SouradniceZnecisteniXstupne": "28,00",
    "SouradniceZnecisteniXminuty": 30,
    "SouradniceZnecisteniXvteriny": "9,00",
    "SouradniceZnecisteniYstupne": "46,00",
    "SouradniceZnecisteniYminuty": 38,
    "SouradniceZnecisteniYvteriny": "1,00",
    "NamorskaVyskaZnecisteniX": 100,
    "ZnecisteniFoto": 4358,
    "OrganleptickeZnecisteni": "",
    "Zakal": "Nimic",
    "ZavadnostMistniInformace": 0,
    "DobraVodaMistniInformace": 1,
    "Teplota": "10,10",
    "EC": "1,89",
    "O2MgL": "8,50",
    "O2procenta": "75,10",
    "pH": "8,11",
    "EH": "68,00",
    "OdberVzorku": "",
    "DatumVznikuZaznmu": "19.2.2015 0:00:00",
    "DatumPosledniUpravy": "19.2.2015 11:30:54",
    "OdberovaSkupina": "U001"
}