{
    "ID": 331,
    "BodRegion": "T",
    "BodRegionCislo": "0328",
    "IdFotografieZdroje": "0827",
    "CisloSANEPID": "",
    "CisloEGHeoM": "",
    "DokumetanceASM": "",
    "DBCisloWaterDataCentreMoldava": "",
    "Obec": "Samurza",
    "ZastupceSamospravy": "Caipac Valentina,029431329",
    "BlizsiLokalizace": "str.Frunze",
    "KatastralniCislo": "",
    "CharekterPozemku": "",
    "SouradniceBobuXstupne": "28,00",
    "SouradniceBobuXminuty": 34,
    "SouradniceBobuXvteriny": "6,00",
    "SouradniceBoduYstupne": "45,00",
    "SouradniceBoduYminuty": 58,
    "SouradniceBoduYvteriny": "34,00",
    "NadmorskaVyskaBodu": 33,
    "DodatkovaInformace": "lantul si caldarea sunt ruginite",
    "CharakterZdrojeVody": "Fântâna săpată",
    "HloubkaStudnyMerena": "8,00",
    "HloubkaStudnyLocalInfo": "11,00",
    "HloubkaHladinyMerena": "11,00",
    "HloubkaHladinyLocalInfo": "8,00",
    "PrumerStudny": "1000,00",
    "VydatnosZdroje": "",
    "VydatnostPokles": 0,
    "HladinaPodzemVody": 0,
    "ZrizovatlZdroje": "localnici",
    "ZrizeniDatum": 1990,
    "ObsluhaObyvatel": 15,
    "DulezitostProObec": "Imporanţă mică – faţă de sursele celelalte",
    "Morfologie": "Suprafaţă plană – câmpie",
    "Pokryv": "Suprafaţa construită urbană/rurală",
    "GeologiePovrch": "Sol",
    "GeologiePodlozi": "",
    "GeologieLitologie": "",
    "GeologieOblast": "",
    "GeologieHydrogeologie": "",
    "HydrogeologieKolektor": "",
    "DokumentaceZdroje": 0,
    "PovrchoveTesneni": "Coroana fântânii cimentată",
    "Plot": "",
    "OchrannePasmo": "",
    "ObecnaOchrana": "",
    "PovrchovaVodaVztah": "Apă de suprafaţă nu se acumulează în împrejurime niciodată",
    "TokVztah": "Nu e inundat niciodata",
    "SilniceVzdalenost": "4,00",
    "ZdrojZnecisteni": "Un alt mod de contaminare – descriere",
    "ZdrojZnecisteniPopis": "drum de tara",
    "SouradniceZnecisteniXstupne": "28,00",
    "SouradniceZnecisteniXminuty": 34,
    "SouradniceZnecisteniXvteriny": "6,00",
    "SouradniceZnecisteniYstupne": "45,00",
    "SouradniceZnecisteniYminuty": 58,
    "SouradniceZnecisteniYvteriny": "34,00",
    "NamorskaVyskaZnecisteniX": 33,
    "ZnecisteniFoto": "0828",
    "OrganleptickeZnecisteni": "nimic",
    "Zakal": "Nimic",
    "ZavadnostMistniInformace": 0,
    "DobraVodaMistniInformace": 1,
    "Teplota": "13,40",
    "EC": "5,36",
    "O2MgL": "6,79",
    "O2procenta": "66,90",
    "pH": "7,87",
    "EH": "118,00",
    "OdberVzorku": "",
    "DatumVznikuZaznmu": "2.6.2014 0:00:00",
    "DatumPosledniUpravy": "2.6.2014 14:17:18",
    "OdberovaSkupina": "U001"
}