{
    "ID": 4853,
    "BodRegion": "Cm",
    "BodRegionCislo": 1593,
    "SampleId": "Cm1593",
    "NazevRegion": "Cimişlia",
    "Obec": "Cimişlia",
    "KatastralniCislo": "",
    "ZastupceSamospravy": "",
    "CisloSANEPID": "",
    "CisloEGHeoM": "",
    "DokumetanceASM": "",
    "DBCisloWaterDataCentreMoldava": "",
    "SouradniceBobuXstupne": 28,
    "SouradniceBobuXminuty": 47,
    "SouradniceBobuXvteriny": 36,
    "SouradniceBoduYstupne": 46,
    "SouradniceBoduYminuty": 31,
    "SouradniceBoduYvteriny": 55,
    "NadmorskaVyskaBodu": 78,
    "IdFotografieZdroje": "115-5134",
    "BlizsiLokalizace": "Fintina este sapata pe str. M.Cogilniceanu 8.",
    "BlizsiLokalizaceCZ": "Studna je v ulici M. Cogilniceanu 8.",
    "DodatkovaInformace": "Coroana fintinii este din beton, are capac de protectie._x000d_\nFintina a fost recent curatita.",
    "DodatkovaInformaceCZ": "Okruží studny je z betonu, má ochranné víko. Studna byla přednedávnem vyčištěna.",
    "CharakterZdrojeVody": "Fântâna săpată",
    "CharakterZdrojeVodyCz": "Kopaná studna",
    "HloubkaHladinyLocalInfo": "",
    "HloubkaHladinyMerena": 3,
    "HloubkaStudnyLocalInfo": "",
    "HloubkaStudnyMerena": 4,
    "PrumerStudny": 1000,
    "VydatnosZdroje": "",
    "VydatnostPokles": "FALSE",
    "HladinaPodzemVody": "FALSE",
    "ZrizovatlZdroje": "",
    "ZrizovatlZdrojeCz": "",
    "ZrizeniDatum": "",
    "ObsluhaObyvatel": 12,
    "DulezitostProObec": "Importanță mică – faţă de sursele celelalte",
    "DůlezitostProObecCz": "Malý význam - vzhledem k ostatním zdrojům",
    "Morfologie": "Depresiunea (teren plat)",
    "Morfologiecz": "V depresi (mělké)",
    "Pokryv": "Suprafaţa construită urbană/rurală",
    "Pokryvcz": "Městská /vesnická zástavba",
    "GeologiePovrch": "Sol",
    "GeologiePovrchCz": "Zemina",
    "Pedologie": "Aluvional",
    "PedologieCz": "Aluviální (fluvizem)",
    "GeologiePodloziSymbol": "N1S3",
    "GeologiePodloziPopis": "Formațiuni sarmațiene superioare,  nisip cuartos, marne",
    "GeologiePodloziPopisCz": "Svrchnosarmatské vrstvy. Křemité písky, pískovce, slíny, sekundární kaoliny, hlíny, vápence.",
    "GeologieLitologieCz": "Jíly s vložkami písků a pískovců",
    "GeologieLitologie": "Argile cu adaos de nisipuri şi gresii",
    "GeologieOblastSymbol": "Zona 1",
    "GeologieOblast": "Răspândirea stratului acvifer cretacic.",
    "GeologieOblastCz": "Hranice rozšíření křídového zvodněného horizontu.",
    "HydrogeologieSymbol": "QIV",
    "HydrogeologieKolektor": "Apele subterane în sedimentele recente. Nisipuri, argile, argile nisipoase.",
    "HydrogeologieKolektorCz": "Podzemní vody v recentních sedimentech. Písky, hlíny, písčité hlíny.",
    "DokumentaceZdroje": "FALSE",
    "PovrchoveTesneni": "Locul săltat al punctului",
    "PovrchoveTesneniCz": "Vyvýšené místo bodu",
    "Plot": "",
    "OchrannePasmo": "",
    "ObecnaOchrana": "",
    "PovrchovaVodaVztah": "Apă de suprafaţă nu se acumulează în împrejurime niciodată",
    "PovrchovaVodaVztahCz": "Povrchová voda se v okolí nikdy nehromadí",
    "TokVztah": "Nu e inundat niciodata",
    "TokVztahCz": "Povodeň nikdy nezaplavuje",
    "SilniceVzdalenost": 2,
    "ZdrojZnecisteni": "",
    "ZdrojZnecistenicz": "",
    "ZdrojZnecisteniPopis": "",
    "ZdrojZnecisteniPopisCz": "",
    "SouradniceZnecisteniXstupne": "",
    "SouradniceZnecisteniXminuty": "",
    "SouradniceZnecisteniXvteriny": "",
    "SouradniceZnecisteniYstupne": "",
    "SouradniceZnecisteniYminuty": "",
    "SouradniceZnecisteniYvteriny": "",
    "NamorskaVyskaZnecisteniX": "",
    "ZnecisteniFoto": "",
    "OrganleptickeZnecisteni": "",
    "OrganoleptickeZnecistenicz": "",
    "Zakal": "Tulbureala uşoară + culoare",
    "ZakalCZ": "Slabý + barva",
    "ZavadnostMistniInformace": "FALSE",
    "DobraVodaMistniInformace": "TRUE",
    "Teplota": 16,
    "EC": 4,
    "O2MgL": 5,
    "O2procenta": 52,
    "pH": 7,
    "EH": 134,
    "cOdberVzorku": "",
    "cOdberVzorkuCz": "",
    "DatumVznikuZaznmu": "8/30/15",
    "DatumPosledniUpravy": "8/30/15",
    "OdberovaSkupina": "U002",
    "Tisk": "",
    "SouradniceBoduX": 28,
    "SouradniceBoduY": 46,
    "SouradniceZnecisteniX": "",
    "SouradniceZnecisteniY": "",
    "rozbory": 1,
    "rozbory2": "",
    "zkontrolováno": 9,
    "kolo_foceni": 1,
    "uuid": "Cm1593"
}