{
    "ID": 749,
    "BodRegion": "Ch",
    "BodRegionCislo": "0192",
    "IdFotografieZdroje": 2091,
    "CisloSANEPID": "",
    "CisloEGHeoM": "",
    "DokumetanceASM": "",
    "DBCisloWaterDataCentreMoldava": "",
    "Obec": "Cucoara",
    "ZastupceSamospravy": "Gota Aliona",
    "BlizsiLokalizace": "raspunzator Primaria",
    "KatastralniCislo": "",
    "CharekterPozemku": "",
    "SouradniceBobuXstupne": "28,00",
    "SouradniceBobuXminuty": 10,
    "SouradniceBobuXvteriny": "7,00",
    "SouradniceBoduYstupne": "46,00",
    "SouradniceBoduYminuty": 3,
    "SouradniceBoduYvteriny": "4,00",
    "NadmorskaVyskaBodu": 17,
    "DodatkovaInformace": "se afla la drum",
    "CharakterZdrojeVody": "Fântâna săpată",
    "HloubkaStudnyMerena": "3,30",
    "HloubkaStudnyLocalInfo": "5,70",
    "HloubkaHladinyMerena": "5,70",
    "HloubkaHladinyLocalInfo": "3,30",
    "PrumerStudny": "1000,00",
    "VydatnosZdroje": "",
    "VydatnostPokles": 0,
    "HladinaPodzemVody": 0,
    "ZrizovatlZdroje": "localnici",
    "ZrizeniDatum": 1970,
    "ObsluhaObyvatel": 10,
    "DulezitostProObec": "Imporanţă mică – faţă de sursele celelalte",
    "Morfologie": "Suprafaţă plană – câmpie",
    "Pokryv": "Suprafaţa construită urbană/rurală",
    "GeologiePovrch": "Sol",
    "GeologiePodlozi": "",
    "GeologieLitologie": "",
    "GeologieOblast": "",
    "GeologieHydrogeologie": "",
    "HydrogeologieKolektor": "",
    "DokumentaceZdroje": 0,
    "PovrchoveTesneni": "Coroana fântânii cimentată",
    "Plot": "",
    "OchrannePasmo": "",
    "ObecnaOchrana": "",
    "PovrchovaVodaVztah": "Apă de suprafaţă nu se acumulează în împrejurime niciodată",
    "TokVztah": "Nu e inundat niciodata",
    "SilniceVzdalenost": "3,00",
    "ZdrojZnecisteni": "Un alt mod de contaminare – descriere",
    "ZdrojZnecisteniPopis": "drum de tara",
    "SouradniceZnecisteniXstupne": "28,00",
    "SouradniceZnecisteniXminuty": 10,
    "SouradniceZnecisteniXvteriny": "7,00",
    "SouradniceZnecisteniYstupne": "46,00",
    "SouradniceZnecisteniYminuty": 3,
    "SouradniceZnecisteniYvteriny": "4,00",
    "NamorskaVyskaZnecisteniX": 17,
    "ZnecisteniFoto": 2092,
    "OrganleptickeZnecisteni": "",
    "Zakal": "Nimic",
    "ZavadnostMistniInformace": 0,
    "DobraVodaMistniInformace": 1,
    "Teplota": "14,40",
    "EC": "4,40",
    "O2MgL": "3,11",
    "O2procenta": "30,50",
    "pH": "7,30",
    "EH": "69,00",
    "OdberVzorku": "",
    "DatumVznikuZaznmu": "14.8.2014 0:00:00",
    "DatumPosledniUpravy": "14.8.2014 8:34:10",
    "OdberovaSkupina": "U001"
}