{
    "ID": 1486,
    "BodRegion": "Lv",
    "BodRegionCislo": "0063",
    "IdFotografieZdroje": 4126,
    "CisloSANEPID": "",
    "CisloEGHeoM": "",
    "DokumetanceASM": "",
    "DBCisloWaterDataCentreMoldava": "",
    "Obec": "Troiţa",
    "ZastupceSamospravy": "Magla Vladimir,primar",
    "BlizsiLokalizace": "pe teritoriul satului",
    "KatastralniCislo": "",
    "CharekterPozemku": "",
    "SouradniceBobuXstupne": "28,00",
    "SouradniceBobuXminuty": 27,
    "SouradniceBobuXvteriny": "49,00",
    "SouradniceBoduYstupne": "46,00",
    "SouradniceBoduYminuty": 34,
    "SouradniceBoduYvteriny": "9,00",
    "NadmorskaVyskaBodu": 44,
    "DodatkovaInformace": "raspunzator primaria",
    "CharakterZdrojeVody": "Fântâna săpată",
    "HloubkaStudnyMerena": "4,30",
    "HloubkaStudnyLocalInfo": "6,50",
    "HloubkaHladinyMerena": "6,50",
    "HloubkaHladinyLocalInfo": "4,30",
    "PrumerStudny": "1000,00",
    "VydatnosZdroje": "",
    "VydatnostPokles": 0,
    "HladinaPodzemVody": 0,
    "ZrizovatlZdroje": "localnici",
    "ZrizeniDatum": 2000,
    "ObsluhaObyvatel": 10,
    "DulezitostProObec": "Imporanţă mică – faţă de sursele celelalte",
    "Morfologie": "Suprafaţă plană – câmpie",
    "Pokryv": "Suprafaţa construită urbană/rurală",
    "GeologiePovrch": "Sol",
    "GeologiePodlozi": "",
    "GeologieLitologie": "",
    "GeologieOblast": "",
    "GeologieHydrogeologie": "",
    "HydrogeologieKolektor": "",
    "DokumentaceZdroje": 0,
    "PovrchoveTesneni": "Coroana fântânii cimentată",
    "Plot": "",
    "OchrannePasmo": "",
    "ObecnaOchrana": "",
    "PovrchovaVodaVztah": "Apă de suprafaţă nu se acumulează în împrejurime niciodată",
    "TokVztah": "Nu e inundat niciodata",
    "SilniceVzdalenost": "6,00",
    "ZdrojZnecisteni": "Un alt mod de contaminare – descriere",
    "ZdrojZnecisteniPopis": "drum de tara",
    "SouradniceZnecisteniXstupne": "28,00",
    "SouradniceZnecisteniXminuty": 27,
    "SouradniceZnecisteniXvteriny": "50,00",
    "SouradniceZnecisteniYstupne": "46,00",
    "SouradniceZnecisteniYminuty": 34,
    "SouradniceZnecisteniYvteriny": "9,00",
    "NamorskaVyskaZnecisteniX": 43,
    "ZnecisteniFoto": 4127,
    "OrganleptickeZnecisteni": "",
    "Zakal": "Nimic",
    "ZavadnostMistniInformace": 0,
    "DobraVodaMistniInformace": 1,
    "Teplota": "9,70",
    "EC": "5,50",
    "O2MgL": "9,86",
    "O2procenta": "88,60",
    "pH": "8,25",
    "EH": "58,00",
    "OdberVzorku": "",
    "DatumVznikuZaznmu": "5.2.2015 0:00:00",
    "DatumPosledniUpravy": "5.2.2015 11:24:31",
    "OdberovaSkupina": "U001"
}