{
    "ID": 10403,
    "BodRegion": "G",
    "BodRegionCislo": 5625,
    "SampleId": "G5625",
    "NazevRegion": "Gagauzia",
    "Obec": "Copceac",
    "KatastralniCislo": "",
    "ZastupceSamospravy": "",
    "CisloSANEPID": "",
    "CisloEGHeoM": "",
    "DokumetanceASM": "",
    "DBCisloWaterDataCentreMoldava": "",
    "SouradniceBobuXstupne": 28,
    "SouradniceBobuXminuty": 40,
    "SouradniceBobuXvteriny": 45,
    "SouradniceBoduYstupne": 45,
    "SouradniceBoduYminuty": 49,
    "SouradniceBoduYvteriny": 54,
    "NadmorskaVyskaBodu": 137,
    "IdFotografieZdroje": "123-7099",
    "BlizsiLokalizace": "Fantana(captaj) este situata la marginea satului, langa fosta crescatorie de porci si langa o gunoiste neautorizata.",
    "BlizsiLokalizaceCZ": "Studna (rezervoár) se nachází na kraji vesnice, vedle bývalého prasečáku a vedle nepovolené skládky (smetiště)",
    "DodatkovaInformace": "Din aceasta fantana la fel se pompeaza in acelasi turn de unde se alimenteaza tot satul._x000d_\nSatul Copceac este conectat la apeduct in proportie de 70%.",
    "DodatkovaInformaceCZ": "Z této studny se voda čerpá také do společného vodojemu, který zásobuje celou vesnici. Vesnice Copceag je ze 70 % napojena na vodovodní síť.",
    "CharakterZdrojeVody": "Fântâna săpată",
    "CharakterZdrojeVodyCz": "Kopaná studna",
    "HloubkaHladinyLocalInfo": "",
    "HloubkaHladinyMerena": 4,
    "HloubkaStudnyLocalInfo": "",
    "HloubkaStudnyMerena": 6,
    "PrumerStudny": "",
    "VydatnosZdroje": "",
    "VydatnostPokles": "FALSE",
    "HladinaPodzemVody": "FALSE",
    "ZrizovatlZdroje": "",
    "ZrizovatlZdrojeCz": "",
    "ZrizeniDatum": "",
    "ObsluhaObyvatel": "",
    "DulezitostProObec": "Sursa cea mai importantă – proba se recoltează totdeauna – serveşte a celor mai mulţi locuitori ai satului",
    "DůlezitostProObecCz": "Nejdůležitější –  vždy se odebírá – slouží pro nejvíce obyvatel obce",
    "Morfologie": "La vale",
    "Morfologiecz": "V údolí",
    "Pokryv": "Suprafaţa construită urbană/rurală",
    "Pokryvcz": "Městská /vesnická zástavba",
    "GeologiePovrch": "Sol",
    "GeologiePovrchCz": "Zemina",
    "Pedologie": "Cernoziom",
    "PedologieCz": "Černozem",
    "GeologiePodloziSymbol": "N2pn",
    "GeologiePodloziPopis": "Formatiuni pontice Calcare, Calcare cu insetii de cochilii, nisipuri, nisip Argilos",
    "GeologiePodloziPopisCz": "Pontské souvrství. Vápence, lasturnaté vápence, písky, hlíny, pískovce.",
    "GeologieLitologieCz": "Jíly s vložkami písků a pískovců",
    "GeologieLitologie": "Argile cu adaos de nisipuri şi gresii",
    "GeologieOblastSymbol": "Zona 3",
    "GeologieOblast": "Răspândirea calcarelor sarmaţiene.",
    "GeologieOblastCz": "Hranice rozšíření sarmatských vápenců.",
    "HydrogeologieSymbol": "N2pn",
    "HydrogeologieKolektor": "Strat acvifer în depozitele pontice. Calcare, nisipuri aleurite.",
    "HydrogeologieKolektorCz": "Zvodněný horizont v uloženinách pontského stupně. Vápence, písky, aleurity.",
    "DokumentaceZdroje": "FALSE",
    "PovrchoveTesneni": "Obiectul închis accesului public",
    "PovrchoveTesneniCz": "Objekt uzavřen proti přístupu",
    "Plot": "",
    "OchrannePasmo": "",
    "ObecnaOchrana": "",
    "PovrchovaVodaVztah": "Apă de suprafaţă nu se acumulează în împrejurime niciodată",
    "PovrchovaVodaVztahCz": "Povrchová voda se v okolí nikdy nehromadí",
    "TokVztah": "Nu e inundat niciodata",
    "TokVztahCz": "Povodeň nikdy nezaplavuje",
    "SilniceVzdalenost": 30,
    "ZdrojZnecisteni": "Un alt mod de contaminare – descriere",
    "ZdrojZnecistenicz": "Jinak znečištěné místo - popsat",
    "ZdrojZnecisteniPopis": "Gunoiste se afla in preajma fantanii.",
    "ZdrojZnecisteniPopisCz": "V blzkosti studny je smetiště.",
    "SouradniceZnecisteniXstupne": 28,
    "SouradniceZnecisteniXminuty": 40,
    "SouradniceZnecisteniXvteriny": 45,
    "SouradniceZnecisteniYstupne": 45,
    "SouradniceZnecisteniYminuty": 49,
    "SouradniceZnecisteniYvteriny": 55,
    "NamorskaVyskaZnecisteniX": 136,
    "ZnecisteniFoto": "123-7100",
    "OrganleptickeZnecisteni": "",
    "OrganoleptickeZnecistenicz": "",
    "Zakal": "Nimic",
    "ZakalCZ": "Žádný",
    "ZavadnostMistniInformace": "FALSE",
    "DobraVodaMistniInformace": "TRUE",
    "Teplota": 14,
    "EC": 2,
    "O2MgL": 8,
    "O2procenta": 82,
    "pH": 7,
    "EH": 79,
    "cOdberVzorku": "Proba de apă de suprafaţă (luată)",
    "cOdberVzorkuCz": "Z volné hladiny - nabrání",
    "DatumVznikuZaznmu": "4/28/16",
    "DatumPosledniUpravy": "4/15/16",
    "OdberovaSkupina": "U002",
    "Tisk": "",
    "SouradniceBoduX": 28,
    "SouradniceBoduY": 45,
    "SouradniceZnecisteniX": 28,
    "SouradniceZnecisteniY": 45,
    "rozbory": 2,
    "rozbory2": "z+r",
    "zkontrolováno": 9,
    "kolo_foceni": 1,
    "uuid": "G5625"
}