{
    "ID": 3332,
    "BodRegion": "Cm",
    "BodRegionCislo": "0934",
    "SampleId": "Cm0934",
    "NazevRegion": "Cimişlia",
    "Obec": "Maximeni",
    "KatastralniCislo": "",
    "ZastupceSamospravy": "",
    "CisloSANEPID": "",
    "CisloEGHeoM": "",
    "DokumetanceASM": "",
    "DBCisloWaterDataCentreMoldava": "",
    "SouradniceBobuXstupne": 28,
    "SouradniceBobuXminuty": 35,
    "SouradniceBobuXvteriny": 50,
    "SouradniceBoduYstupne": 46,
    "SouradniceBoduYminuty": 34,
    "SouradniceBoduYvteriny": 30,
    "NadmorskaVyskaBodu": 139,
    "IdFotografieZdroje": "113-4106",
    "BlizsiLokalizace": "Fintina este sapata la marginea drumului local, in apropierea caselor.",
    "BlizsiLokalizaceCZ": "Studna se nachází na kraji místní cesty, v blízkosti domů.",
    "DodatkovaInformace": "Fintina are capaca de protectie, coroana este din lemn, lantul prezinta rugina._x000d_\nSursa de apa este construita din piatra.",
    "DodatkovaInformaceCZ": "Studna má ochranné víko, okruží je ze dřeva, řetěz je zrezavělý. Je postavena z kamene.",
    "CharakterZdrojeVody": "Fântâna săpată",
    "CharakterZdrojeVodyCz": "Kopaná studna",
    "HloubkaHladinyLocalInfo": "",
    "HloubkaHladinyMerena": 3,
    "HloubkaStudnyLocalInfo": "",
    "HloubkaStudnyMerena": 4,
    "PrumerStudny": 700,
    "VydatnosZdroje": "",
    "VydatnostPokles": "FALSE",
    "HladinaPodzemVody": "FALSE",
    "ZrizovatlZdroje": "Locuitorii satului",
    "ZrizovatlZdrojeCz": "Obyvatelé obce",
    "ZrizeniDatum": "",
    "ObsluhaObyvatel": 11,
    "DulezitostProObec": "Importanță mică – faţă de sursele celelalte",
    "DůlezitostProObecCz": "Malý význam - vzhledem k ostatním zdrojům",
    "Morfologie": "La vale",
    "Morfologiecz": "V údolí",
    "Pokryv": "Suprafaţa construită urbană/rurală",
    "Pokryvcz": "Městská /vesnická zástavba",
    "GeologiePovrch": "Sol",
    "GeologiePovrchCz": "Zemina",
    "Pedologie": "Neclasificat",
    "PedologieCz": "Neklasifikováno (zástavba)",
    "GeologiePodloziSymbol": "N1S3",
    "GeologiePodloziPopis": "Formațiuni sarmațiene superioare,  nisip cuartos, marne",
    "GeologiePodloziPopisCz": "Svrchnosarmatské vrstvy. Křemité písky, pískovce, slíny, sekundární kaoliny, hlíny, vápence.",
    "GeologieLitologieCz": "Jíly s vložkami písků a pískovců",
    "GeologieLitologie": "Argile cu adaos de nisipuri şi gresii",
    "GeologieOblastSymbol": "Zona 1",
    "GeologieOblast": "Răspândirea stratului acvifer cretacic.",
    "GeologieOblastCz": "Hranice rozšíření křídového zvodněného horizontu.",
    "HydrogeologieSymbol": "N1S3+m",
    "HydrogeologieKolektor": "Strat acvifer în depozitele sarmaţiene şi meoţiene superioare.",
    "HydrogeologieKolektorCz": "Zvodněný horizont v uloženinách svrchního sarmatu a meotu.",
    "DokumentaceZdroje": "FALSE",
    "PovrchoveTesneni": "Locul săltat al punctului",
    "PovrchoveTesneniCz": "Vyvýšené místo bodu",
    "Plot": "",
    "OchrannePasmo": "",
    "ObecnaOchrana": "",
    "PovrchovaVodaVztah": "Apă de suprafaţă nu se acumulează în împrejurime niciodată",
    "PovrchovaVodaVztahCz": "Povrchová voda se v okolí nikdy nehromadí",
    "TokVztah": "Nu e inundat niciodata",
    "TokVztahCz": "Povodeň nikdy nezaplavuje",
    "SilniceVzdalenost": 2,
    "ZdrojZnecisteni": "",
    "ZdrojZnecistenicz": "",
    "ZdrojZnecisteniPopis": "",
    "ZdrojZnecisteniPopisCz": "",
    "SouradniceZnecisteniXstupne": "",
    "SouradniceZnecisteniXminuty": "",
    "SouradniceZnecisteniXvteriny": "",
    "SouradniceZnecisteniYstupne": "",
    "SouradniceZnecisteniYminuty": "",
    "SouradniceZnecisteniYvteriny": "",
    "NamorskaVyskaZnecisteniX": "",
    "ZnecisteniFoto": "",
    "OrganleptickeZnecisteni": "",
    "OrganoleptickeZnecistenicz": "",
    "Zakal": "Nimic",
    "ZakalCZ": "Žádný",
    "ZavadnostMistniInformace": "FALSE",
    "DobraVodaMistniInformace": "TRUE",
    "Teplota": 12,
    "EC": 3,
    "O2MgL": 4,
    "O2procenta": 42,
    "pH": 7,
    "EH": 380,
    "cOdberVzorku": "",
    "cOdberVzorkuCz": "",
    "DatumVznikuZaznmu": "6/12/15",
    "DatumPosledniUpravy": "6/4/15",
    "OdberovaSkupina": "U002",
    "Tisk": "",
    "SouradniceBoduX": 28,
    "SouradniceBoduY": 46,
    "SouradniceZnecisteniX": "",
    "SouradniceZnecisteniY": "",
    "rozbory": 1,
    "rozbory2": "",
    "zkontrolováno": 9,
    "uuid": "Cm0934"
}