{
    "ID": 54,
    "BodRegion": "T",
    "BodRegionCislo": "0053",
    "IdFotografieZdroje": "0134",
    "CisloSANEPID": "",
    "CisloEGHeoM": "",
    "DokumetanceASM": "",
    "DBCisloWaterDataCentreMoldava": "",
    "Obec": "Novosiolovca",
    "ZastupceSamospravy": "Casandrac Nina,029434196",
    "BlizsiLokalizace": "str.Comsomoloiscaia 11",
    "KatastralniCislo": "",
    "CharekterPozemku": "",
    "SouradniceBobuXstupne": "28,00",
    "SouradniceBobuXminuty": 35,
    "SouradniceBobuXvteriny": "52,00",
    "SouradniceBoduYstupne": "45,00",
    "SouradniceBoduYminuty": 54,
    "SouradniceBoduYvteriny": "4,00",
    "NadmorskaVyskaBodu": 22,
    "DodatkovaInformace": "",
    "CharakterZdrojeVody": "Fântâna săpată",
    "HloubkaStudnyMerena": "7,60",
    "HloubkaStudnyLocalInfo": "8,50",
    "HloubkaHladinyMerena": "8,50",
    "HloubkaHladinyLocalInfo": "7,60",
    "PrumerStudny": "800,00",
    "VydatnosZdroje": "",
    "VydatnostPokles": 0,
    "HladinaPodzemVody": 0,
    "ZrizovatlZdroje": "Ripisciuc Vladimir",
    "ZrizeniDatum": 2003,
    "ObsluhaObyvatel": 14,
    "DulezitostProObec": "Imporanţă mică – faţă de sursele celelalte",
    "Morfologie": "Suprafaţă plană – câmpie",
    "Pokryv": "Suprafaţa construită urbană/rurală",
    "GeologiePovrch": "Sol",
    "GeologiePodlozi": "",
    "GeologieLitologie": "",
    "GeologieOblast": "",
    "GeologieHydrogeologie": "",
    "HydrogeologieKolektor": "",
    "DokumentaceZdroje": 0,
    "PovrchoveTesneni": "Coroana fântânii cimentată",
    "Plot": "",
    "OchrannePasmo": "",
    "ObecnaOchrana": "",
    "PovrchovaVodaVztah": "Apă de suprafaţă nu se acumulează în împrejurime niciodată",
    "TokVztah": "Nu e inundat niciodata",
    "SilniceVzdalenost": "35,00",
    "ZdrojZnecisteni": "Un alt mod de contaminare – descriere",
    "ZdrojZnecisteniPopis": "gradina particulara",
    "SouradniceZnecisteniXstupne": "28,00",
    "SouradniceZnecisteniXminuty": 35,
    "SouradniceZnecisteniXvteriny": "53,00",
    "SouradniceZnecisteniYstupne": "45,00",
    "SouradniceZnecisteniYminuty": 54,
    "SouradniceZnecisteniYvteriny": "5,00",
    "NamorskaVyskaZnecisteniX": 22,
    "ZnecisteniFoto": "0135",
    "OrganleptickeZnecisteni": "nimic",
    "Zakal": "Nimic",
    "ZavadnostMistniInformace": 0,
    "DobraVodaMistniInformace": 1,
    "Teplota": "12,40",
    "EC": "4,43",
    "O2MgL": "7,34",
    "O2procenta": "71,00",
    "pH": "7,40",
    "EH": "147,00",
    "OdberVzorku": "",
    "DatumVznikuZaznmu": "23.4.2014 0:00:00",
    "DatumPosledniUpravy": "23.4.2014 10:06:17",
    "OdberovaSkupina": "U001"
}