{
    "ID": 205,
    "BodRegion": "T",
    "BodRegionCislo": "0203",
    "IdFotografieZdroje": "0482",
    "CisloSANEPID": "",
    "CisloEGHeoM": "",
    "DokumetanceASM": "",
    "DBCisloWaterDataCentreMoldava": "",
    "Obec": "Ciumai",
    "ZastupceSamospravy": "Turcan Tatiana,078800288",
    "BlizsiLokalizace": "str.Gagarina77",
    "KatastralniCislo": "",
    "CharekterPozemku": "",
    "SouradniceBobuXstupne": "28,00",
    "SouradniceBobuXminuty": 34,
    "SouradniceBobuXvteriny": "6,00",
    "SouradniceBoduYstupne": "45,00",
    "SouradniceBoduYminuty": 46,
    "SouradniceBoduYvteriny": "39,00",
    "NadmorskaVyskaBodu": 20,
    "DodatkovaInformace": "",
    "CharakterZdrojeVody": "Fântâna săpată",
    "HloubkaStudnyMerena": "5,00",
    "HloubkaStudnyLocalInfo": "8,00",
    "HloubkaHladinyMerena": "8,00",
    "HloubkaHladinyLocalInfo": "5,00",
    "PrumerStudny": "1500,00",
    "VydatnosZdroje": "",
    "VydatnostPokles": 0,
    "HladinaPodzemVody": 0,
    "ZrizovatlZdroje": "Sacali Alexei",
    "ZrizeniDatum": 1970,
    "ObsluhaObyvatel": 10,
    "DulezitostProObec": "Imporanţă mică – faţă de sursele celelalte",
    "Morfologie": "Suprafaţă plană – câmpie",
    "Pokryv": "Suprafaţa construită urbană/rurală",
    "GeologiePovrch": "Sol",
    "GeologiePodlozi": "",
    "GeologieLitologie": "",
    "GeologieOblast": "",
    "GeologieHydrogeologie": "",
    "HydrogeologieKolektor": "",
    "DokumentaceZdroje": 0,
    "PovrchoveTesneni": "Coroana fântânii cimentată",
    "Plot": "",
    "OchrannePasmo": "",
    "ObecnaOchrana": "",
    "PovrchovaVodaVztah": "Apă de suprafaţă nu se acumulează în împrejurime niciodată",
    "TokVztah": "Nu e inundat niciodata",
    "SilniceVzdalenost": "14,00",
    "ZdrojZnecisteni": "Un alt mod de contaminare – descriere",
    "ZdrojZnecisteniPopis": "gradina particulara",
    "SouradniceZnecisteniXstupne": "28,00",
    "SouradniceZnecisteniXminuty": 34,
    "SouradniceZnecisteniXvteriny": "6,00",
    "SouradniceZnecisteniYstupne": "45,00",
    "SouradniceZnecisteniYminuty": 46,
    "SouradniceZnecisteniYvteriny": "39,00",
    "NamorskaVyskaZnecisteniX": 20,
    "ZnecisteniFoto": "0483",
    "OrganleptickeZnecisteni": "nimic",
    "Zakal": "Nimic",
    "ZavadnostMistniInformace": 0,
    "DobraVodaMistniInformace": 1,
    "Teplota": "15,00",
    "EC": "2,67",
    "O2MgL": "8,12",
    "O2procenta": "80,10",
    "pH": "7,75",
    "EH": "226,00",
    "OdberVzorku": "",
    "DatumVznikuZaznmu": "13.5.2014 0:00:00",
    "DatumPosledniUpravy": "13.5.2014 14:38:27",
    "OdberovaSkupina": "U001"
}