{
    "ID": 995,
    "BodRegion": "Ch",
    "BodRegionCislo": "0438",
    "IdFotografieZdroje": 2841,
    "CisloSANEPID": "",
    "CisloEGHeoM": "",
    "DokumetanceASM": "",
    "DBCisloWaterDataCentreMoldava": "",
    "Obec": "Larga Nouă",
    "ZastupceSamospravy": "Stoianov Nicolai",
    "BlizsiLokalizace": "raspunzator Primaria",
    "KatastralniCislo": "",
    "CharekterPozemku": "",
    "SouradniceBobuXstupne": "28,00",
    "SouradniceBobuXminuty": 13,
    "SouradniceBobuXvteriny": "35,00",
    "SouradniceBoduYstupne": "46,00",
    "SouradniceBoduYminuty": 4,
    "SouradniceBoduYvteriny": "34,00",
    "NadmorskaVyskaBodu": 64,
    "DodatkovaInformace": "se afla la drum",
    "CharakterZdrojeVody": "Fântâna săpată",
    "HloubkaStudnyMerena": "5,10",
    "HloubkaStudnyLocalInfo": "7,00",
    "HloubkaHladinyMerena": "7,00",
    "HloubkaHladinyLocalInfo": "5,10",
    "PrumerStudny": "1000,00",
    "VydatnosZdroje": "",
    "VydatnostPokles": 0,
    "HladinaPodzemVody": 0,
    "ZrizovatlZdroje": "localnici",
    "ZrizeniDatum": 1970,
    "ObsluhaObyvatel": 10,
    "DulezitostProObec": "Imporanţă mică – faţă de sursele celelalte",
    "Morfologie": "Suprafaţă plană – câmpie",
    "Pokryv": "Suprafaţa construită urbană/rurală",
    "GeologiePovrch": "Sol",
    "GeologiePodlozi": "",
    "GeologieLitologie": "",
    "GeologieOblast": "",
    "GeologieHydrogeologie": "",
    "HydrogeologieKolektor": "",
    "DokumentaceZdroje": 0,
    "PovrchoveTesneni": "Coroana fântânii cimentată",
    "Plot": "",
    "OchrannePasmo": "",
    "ObecnaOchrana": "",
    "PovrchovaVodaVztah": "Apă de suprafaţă nu se acumulează în împrejurime niciodată",
    "TokVztah": "Nu e inundat niciodata",
    "SilniceVzdalenost": "5,00",
    "ZdrojZnecisteni": "Un alt mod de contaminare – descriere",
    "ZdrojZnecisteniPopis": "drum de tara",
    "SouradniceZnecisteniXstupne": "28,00",
    "SouradniceZnecisteniXminuty": 13,
    "SouradniceZnecisteniXvteriny": "35,00",
    "SouradniceZnecisteniYstupne": "46,00",
    "SouradniceZnecisteniYminuty": 4,
    "SouradniceZnecisteniYvteriny": "34,00",
    "NamorskaVyskaZnecisteniX": 64,
    "ZnecisteniFoto": 2842,
    "OrganleptickeZnecisteni": "",
    "Zakal": "Nimic",
    "ZavadnostMistniInformace": 0,
    "DobraVodaMistniInformace": 1,
    "Teplota": "13,00",
    "EC": "2,84",
    "O2MgL": "6,14",
    "O2procenta": "59,20",
    "pH": "7,10",
    "EH": "-39,00",
    "OdberVzorku": "",
    "DatumVznikuZaznmu": "23.9.2014 0:00:00",
    "DatumPosledniUpravy": "23.9.2014 10:59:30",
    "OdberovaSkupina": "U001"
}