{
    "ID": 766,
    "BodRegion": "Ch",
    "BodRegionCislo": "0209",
    "IdFotografieZdroje": 2145,
    "CisloSANEPID": "",
    "CisloEGHeoM": "",
    "DokumetanceASM": "",
    "DBCisloWaterDataCentreMoldava": "",
    "Obec": "Baurci-Moldoveni",
    "ZastupceSamospravy": "Rosca Pavel",
    "BlizsiLokalizace": "raspunzator Primaria",
    "KatastralniCislo": "",
    "CharekterPozemku": "",
    "SouradniceBobuXstupne": "28,00",
    "SouradniceBobuXminuty": 12,
    "SouradniceBobuXvteriny": "18,00",
    "SouradniceBoduYstupne": "46,00",
    "SouradniceBoduYminuty": 1,
    "SouradniceBoduYvteriny": "34,00",
    "NadmorskaVyskaBodu": 65,
    "DodatkovaInformace": "se afla la drum",
    "CharakterZdrojeVody": "Fântâna săpată",
    "HloubkaStudnyMerena": "4,90",
    "HloubkaStudnyLocalInfo": "7,00",
    "HloubkaHladinyMerena": "7,00",
    "HloubkaHladinyLocalInfo": "4,90",
    "PrumerStudny": "1000,00",
    "VydatnosZdroje": "",
    "VydatnostPokles": 0,
    "HladinaPodzemVody": 0,
    "ZrizovatlZdroje": "localnici",
    "ZrizeniDatum": 1960,
    "ObsluhaObyvatel": 15,
    "DulezitostProObec": "Imporanţă mică – faţă de sursele celelalte",
    "Morfologie": "Suprafaţă plană – câmpie",
    "Pokryv": "Suprafaţa construită urbană/rurală",
    "GeologiePovrch": "Sol",
    "GeologiePodlozi": "",
    "GeologieLitologie": "",
    "GeologieOblast": "",
    "GeologieHydrogeologie": "",
    "HydrogeologieKolektor": "",
    "DokumentaceZdroje": 0,
    "PovrchoveTesneni": "Coroana fântânii cimentată",
    "Plot": "",
    "OchrannePasmo": "",
    "ObecnaOchrana": "",
    "PovrchovaVodaVztah": "Apă de suprafaţă nu se acumulează în împrejurime niciodată",
    "TokVztah": "Nu e inundat niciodata",
    "SilniceVzdalenost": "5,00",
    "ZdrojZnecisteni": "Un alt mod de contaminare – descriere",
    "ZdrojZnecisteniPopis": "drum de tara",
    "SouradniceZnecisteniXstupne": "28,00",
    "SouradniceZnecisteniXminuty": 12,
    "SouradniceZnecisteniXvteriny": "18,00",
    "SouradniceZnecisteniYstupne": "46,00",
    "SouradniceZnecisteniYminuty": 1,
    "SouradniceZnecisteniYvteriny": "34,00",
    "NamorskaVyskaZnecisteniX": 65,
    "ZnecisteniFoto": 2146,
    "OrganleptickeZnecisteni": "",
    "Zakal": "Nimic",
    "ZavadnostMistniInformace": 0,
    "DobraVodaMistniInformace": 1,
    "Teplota": "13,20",
    "EC": "3,80",
    "O2MgL": "4,95",
    "O2procenta": "47,10",
    "pH": "7,30",
    "EH": "54,00",
    "OdberVzorku": "",
    "DatumVznikuZaznmu": "22.8.2014 0:00:00",
    "DatumPosledniUpravy": "22.8.2014 10:07:23",
    "OdberovaSkupina": "U001"
}