{
    "ID": 1333,
    "BodRegion": "Ch",
    "BodRegionCislo": "0776",
    "IdFotografieZdroje": 3707,
    "CisloSANEPID": "",
    "CisloEGHeoM": "",
    "DokumetanceASM": "",
    "DBCisloWaterDataCentreMoldava": "",
    "Obec": "Burlăceni",
    "ZastupceSamospravy": "Gaidarli Vasile",
    "BlizsiLokalizace": "raspunzator firma",
    "KatastralniCislo": "",
    "CharekterPozemku": "",
    "SouradniceBobuXstupne": "28,00",
    "SouradniceBobuXminuty": 30,
    "SouradniceBobuXvteriny": "0,00",
    "SouradniceBoduYstupne": "45,00",
    "SouradniceBoduYminuty": 45,
    "SouradniceBoduYvteriny": "24,00",
    "NadmorskaVyskaBodu": 112,
    "DodatkovaInformace": "se afla la drum\r\nsonda",
    "CharakterZdrojeVody": "Foraj",
    "HloubkaStudnyMerena": "180,00",
    "HloubkaStudnyLocalInfo": "220,00",
    "HloubkaHladinyMerena": "220,00",
    "HloubkaHladinyLocalInfo": "180,00",
    "PrumerStudny": "500,00",
    "VydatnosZdroje": "2,77",
    "VydatnostPokles": 0,
    "HladinaPodzemVody": 0,
    "ZrizovatlZdroje": "SRL Agroilici",
    "ZrizeniDatum": 1989,
    "ObsluhaObyvatel": 400,
    "DulezitostProObec": "Sursa cea mai importantă – proba se recoltează totdeauna – serveşte a celor mai mulţi locuitori ai satului",
    "Morfologie": "Suprafaţă plană – câmpie",
    "Pokryv": "Suprafaţa construită urbană/rurală",
    "GeologiePovrch": "Sol",
    "GeologiePodlozi": "",
    "GeologieLitologie": "",
    "GeologieOblast": "",
    "GeologieHydrogeologie": "",
    "HydrogeologieKolektor": "",
    "DokumentaceZdroje": 0,
    "PovrchoveTesneni": "Bloc de ciment al forajului",
    "Plot": "0,00",
    "OchrannePasmo": "0,00",
    "ObecnaOchrana": 0,
    "PovrchovaVodaVztah": "Apă de suprafaţă nu se acumulează în împrejurime niciodată",
    "TokVztah": "Nu e inundat niciodata",
    "SilniceVzdalenost": "15,00",
    "ZdrojZnecisteni": "Un alt mod de contaminare – descriere",
    "ZdrojZnecisteniPopis": "cimp",
    "SouradniceZnecisteniXstupne": "28,00",
    "SouradniceZnecisteniXminuty": 30,
    "SouradniceZnecisteniXvteriny": "0,00",
    "SouradniceZnecisteniYstupne": "45,00",
    "SouradniceZnecisteniYminuty": 45,
    "SouradniceZnecisteniYvteriny": "24,00",
    "NamorskaVyskaZnecisteniX": 112,
    "ZnecisteniFoto": 3708,
    "OrganleptickeZnecisteni": "",
    "Zakal": "Nimic",
    "ZavadnostMistniInformace": 0,
    "DobraVodaMistniInformace": 1,
    "Teplota": "14,60",
    "EC": "2,32",
    "O2MgL": "6,56",
    "O2procenta": "64,90",
    "pH": "7,87",
    "EH": "126,00",
    "OdberVzorku": "Din apă curgătoare – robinet, apa adusă prin conducta izvorului",
    "DatumVznikuZaznmu": "4.11.2014 0:00:00",
    "DatumPosledniUpravy": "4.11.2014 15:00:14",
    "OdberovaSkupina": "U001"
}