{
    "ID": 6351,
    "BodRegion": "B",
    "BodRegionCislo": "0291",
    "SampleId": "B0291",
    "NazevRegion": "Basarabeasca",
    "Obec": "Başcalia",
    "KatastralniCislo": "",
    "ZastupceSamospravy": "",
    "CisloSANEPID": "",
    "CisloEGHeoM": "",
    "DokumetanceASM": "",
    "DBCisloWaterDataCentreMoldava": "",
    "SouradniceBobuXstupne": 28,
    "SouradniceBobuXminuty": 47,
    "SouradniceBobuXvteriny": 17,
    "SouradniceBoduYstupne": 46,
    "SouradniceBoduYminuty": 18,
    "SouradniceBoduYvteriny": 30,
    "NadmorskaVyskaBodu": 135,
    "IdFotografieZdroje": "117-5640",
    "BlizsiLokalizace": "Fintina este situata in apropierea caselor, la marginea drumului local.",
    "BlizsiLokalizaceCZ": "Studna se nachází v blízkosti domů, na kraji místní cesty.",
    "DodatkovaInformace": "Fintina este partial ingradita, scripetele si lantul este ruginit._x000d_\nSursa de apa are acoperis de protectie.",
    "DodatkovaInformaceCZ": "Studna je částečně oplocená, kladka a řetěz jsou zrezavělé. Má ochrannou stříšku.",
    "CharakterZdrojeVody": "Fântâna săpată",
    "CharakterZdrojeVodyCz": "Kopaná studna",
    "HloubkaHladinyLocalInfo": "",
    "HloubkaHladinyMerena": 4,
    "HloubkaStudnyLocalInfo": "",
    "HloubkaStudnyMerena": 9,
    "PrumerStudny": 1000,
    "VydatnosZdroje": "",
    "VydatnostPokles": "FALSE",
    "HladinaPodzemVody": "FALSE",
    "ZrizovatlZdroje": "Locuitorii satului",
    "ZrizovatlZdrojeCz": "Obyvatelé vesnice",
    "ZrizeniDatum": "",
    "ObsluhaObyvatel": 10,
    "DulezitostProObec": "Una dintre cele importante – proba se recoltează ca a două în cazul când în comună există mai mult",
    "DůlezitostProObecCz": "Jeden z důležitých – odebírá se jako druhý v případě, že v obci je vice než 10 zdrojů a není mimo nejdůležitější odebrán zdroj označený jako rizikový – blíže než 50 m od silnice, nebo u identifikovaného nebo potenciálního zdroje znečištění",
    "Morfologie": "Depresiunea (teren plat)",
    "Morfologiecz": "V depresi (mělké)",
    "Pokryv": "Suprafaţa construită urbană/rurală",
    "Pokryvcz": "Městská /vesnická zástavba",
    "GeologiePovrch": "Sol",
    "GeologiePovrchCz": "Zemina",
    "Pedologie": "Neclasificat",
    "PedologieCz": "Neklasifikováno (zástavba)",
    "GeologiePodloziSymbol": "N1S3",
    "GeologiePodloziPopis": "Formațiuni sarmațiene superioare,  nisip cuartos, marne",
    "GeologiePodloziPopisCz": "Svrchnosarmatské vrstvy. Křemité písky, pískovce, slíny, sekundární kaoliny, hlíny, vápence.",
    "GeologieLitologieCz": "Jíly s vložkami písků a pískovců",
    "GeologieLitologie": "Argile cu adaos de nisipuri şi gresii",
    "GeologieOblastSymbol": "Zona 1",
    "GeologieOblast": "Răspândirea stratului acvifer cretacic.",
    "GeologieOblastCz": "Hranice rozšíření křídového zvodněného horizontu.",
    "HydrogeologieSymbol": "N1S3+m",
    "HydrogeologieKolektor": "Strat acvifer în depozitele sarmaţiene şi meoţiene superioare.",
    "HydrogeologieKolektorCz": "Zvodněný horizont v uloženinách svrchního sarmatu a meotu.",
    "DokumentaceZdroje": "FALSE",
    "PovrchoveTesneni": "Coroana fântânii cimentată",
    "PovrchoveTesneniCz": "Cementované mezikruží studny",
    "Plot": "",
    "OchrannePasmo": "",
    "ObecnaOchrana": "",
    "PovrchovaVodaVztah": "Apă de suprafaţă nu se acumulează în împrejurime niciodată",
    "PovrchovaVodaVztahCz": "Povrchová voda se v okolí nikdy nehromadí",
    "TokVztah": "Nu e inundat niciodata",
    "TokVztahCz": "Povodeň nikdy nezaplavuje",
    "SilniceVzdalenost": 2,
    "ZdrojZnecisteni": "",
    "ZdrojZnecistenicz": "",
    "ZdrojZnecisteniPopis": "",
    "ZdrojZnecisteniPopisCz": "",
    "SouradniceZnecisteniXstupne": "",
    "SouradniceZnecisteniXminuty": "",
    "SouradniceZnecisteniXvteriny": "",
    "SouradniceZnecisteniYstupne": "",
    "SouradniceZnecisteniYminuty": "",
    "SouradniceZnecisteniYvteriny": "",
    "NamorskaVyskaZnecisteniX": "",
    "ZnecisteniFoto": "",
    "OrganleptickeZnecisteni": "",
    "OrganoleptickeZnecistenicz": "",
    "Zakal": "Nimic",
    "ZakalCZ": "Žádný",
    "ZavadnostMistniInformace": "FALSE",
    "DobraVodaMistniInformace": "TRUE",
    "Teplota": 12,
    "EC": 4,
    "O2MgL": 1,
    "O2procenta": 18,
    "pH": 7,
    "EH": 163,
    "cOdberVzorku": "Proba de apă de suprafaţă (luată)",
    "cOdberVzorkuCz": "Z volné hladiny - nabrání",
    "DatumVznikuZaznmu": "10/14/15",
    "DatumPosledniUpravy": "10/2/15",
    "OdberovaSkupina": "U002",
    "Tisk": "",
    "SouradniceBoduX": 28,
    "SouradniceBoduY": 46,
    "SouradniceZnecisteniX": "",
    "SouradniceZnecisteniY": "",
    "rozbory": 1,
    "rozbory2": "z",
    "zkontrolováno": 9,
    "kolo_foceni": 1,
    "uuid": "B0291"
}