{
    "ID": 246,
    "BodRegion": "T",
    "BodRegionCislo": "0244",
    "IdFotografieZdroje": "0583",
    "CisloSANEPID": "",
    "CisloEGHeoM": "",
    "DokumetanceASM": "",
    "DBCisloWaterDataCentreMoldava": "",
    "Obec": "Hîrtop",
    "ZastupceSamospravy": "Duscov Dumitru,069572361",
    "BlizsiLokalizace": "str.Tataru Ion",
    "KatastralniCislo": "",
    "CharekterPozemku": "",
    "SouradniceBobuXstupne": "28,00",
    "SouradniceBobuXminuty": 29,
    "SouradniceBobuXvteriny": "32,00",
    "SouradniceBoduYstupne": "45,00",
    "SouradniceBoduYminuty": 55,
    "SouradniceBoduYvteriny": "4,00",
    "NadmorskaVyskaBodu": 47,
    "DodatkovaInformace": "",
    "CharakterZdrojeVody": "Fântâna săpată",
    "HloubkaStudnyMerena": "4,00",
    "HloubkaStudnyLocalInfo": "8,00",
    "HloubkaHladinyMerena": "8,00",
    "HloubkaHladinyLocalInfo": "4,00",
    "PrumerStudny": "1000,00",
    "VydatnosZdroje": "",
    "VydatnostPokles": 0,
    "HladinaPodzemVody": 0,
    "ZrizovatlZdroje": "localnicii",
    "ZrizeniDatum": 1990,
    "ObsluhaObyvatel": 10,
    "DulezitostProObec": "Imporanţă mică – faţă de sursele celelalte",
    "Morfologie": "Suprafaţă plană – câmpie",
    "Pokryv": "Suprafaţa construită urbană/rurală",
    "GeologiePovrch": "Sol",
    "GeologiePodlozi": "",
    "GeologieLitologie": "",
    "GeologieOblast": "",
    "GeologieHydrogeologie": "",
    "HydrogeologieKolektor": "",
    "DokumentaceZdroje": 0,
    "PovrchoveTesneni": "Coroana fântânii cimentată",
    "Plot": "",
    "OchrannePasmo": "",
    "ObecnaOchrana": "",
    "PovrchovaVodaVztah": "Apă de suprafaţă nu se acumulează în împrejurime niciodată",
    "TokVztah": "Nu e inundat niciodata",
    "SilniceVzdalenost": "3,00",
    "ZdrojZnecisteni": "Un alt mod de contaminare – descriere",
    "ZdrojZnecisteniPopis": "gradina particulara",
    "SouradniceZnecisteniXstupne": "28,00",
    "SouradniceZnecisteniXminuty": 29,
    "SouradniceZnecisteniXvteriny": "32,00",
    "SouradniceZnecisteniYstupne": "45,00",
    "SouradniceZnecisteniYminuty": 55,
    "SouradniceZnecisteniYvteriny": "4,00",
    "NamorskaVyskaZnecisteniX": 47,
    "ZnecisteniFoto": "0584",
    "OrganleptickeZnecisteni": "nimic",
    "Zakal": "Nimic",
    "ZavadnostMistniInformace": 0,
    "DobraVodaMistniInformace": 1,
    "Teplota": "12,50",
    "EC": "5,01",
    "O2MgL": "7,66",
    "O2procenta": "72,00",
    "pH": "7,90",
    "EH": "174,00",
    "OdberVzorku": "",
    "DatumVznikuZaznmu": "21.5.2014 0:00:00",
    "DatumPosledniUpravy": "21.5.2014 16:34:34",
    "OdberovaSkupina": "U001"
}